kindlestrip.py
kindlestrip-1.38.0.dist-info/LICENSE
kindlestrip-1.38.0.dist-info/METADATA
kindlestrip-1.38.0.dist-info/WHEEL
kindlestrip-1.38.0.dist-info/entry_points.txt
kindlestrip-1.38.0.dist-info/top_level.txt
kindlestrip-1.38.0.dist-info/RECORD
