Metadata-Version: 2.1
Name: kindlestrip
Version: 1.38.0
Summary: Strips the penultimate record from Mobipocket ebooks
Home-page: https://github.com/jefftriplett/kindlestrip
Author: Paul Durrant
Maintainer: Jeff Triplett
Maintainer-email: jeff.triplett@gmail.com
License: Unlicense
Platform: UNKNOWN
Classifier: Development Status :: 5 - Production/Stable
Classifier: Environment :: Web Environment
Classifier: Intended Audience :: Developers
Classifier: License :: Public Domain
Classifier: Operating System :: OS Independent
Classifier: Programming Language :: Python :: 3
Classifier: Programming Language :: Python :: 3 :: Only
Classifier: Programming Language :: Python :: 3.7
Classifier: Programming Language :: Python :: 3.8
Classifier: Programming Language :: Python :: 3.9
Classifier: Programming Language :: Python :: 3.10
Classifier: Programming Language :: Python :: Implementation :: CPython
Classifier: Topic :: Utilities
Requires-Python: >=3.7
License-File: LICENSE
